<?xml version="1.0" encoding="utf-8"?>
<!DOCTYPE hibernate-mapping PUBLIC "-//Hibernate/Hibernate Mapping DTD 3.0//EN"
"http://hibernate.sourceforge.net/hibernate-mapping-3.0.dtd">
<!-- 
    Mapping file autogenerated by MyEclipse Persistence Tools
-->
<hibernate-mapping>
    <class name="aute.openapi.entities.PerfStation" table="perf_station" catalog="openapi">
        <id name="id" type="java.lang.Integer">
            <column name="id" />
            <generator class="identity" />
        </id>
        <property name="mac" type="java.lang.String">
            <column name="mac" length="30" not-null="true">
                <comment>用户mac</comment>
            </column>
        </property>
        <property name="apMac" type="java.lang.String">
            <column name="apMac" length="30">
                <comment>AP mac</comment>
            </column>
        </property>
        <property name="wtpBelongApId" type="java.lang.String">
            <column name="wtpBelongApId" length="30" />
        </property>
        <property name="acIp" type="java.lang.String">
            <column name="acIp" length="30">
                <comment>AC IP</comment>
            </column>
        </property>
        <property name="collTime" type="java.sql.Timestamp">
            <column name="collTime" length="19" not-null="true" />
        </property>
        <property name="staIp" type="java.lang.String">
            <column name="staIp" length="30">
                <comment>用户IP</comment>
            </column>
        </property>
        <property name="ssid" type="java.lang.String">
            <column name="ssid" length="30">
                <comment>用户接入的ssid</comment>
            </column>
        </property>
        <property name="staRadioMode" type="java.lang.String">
            <column name="staRadioMode" length="30">
                <comment>用户无线信道模式（采用的协议）</comment>
            </column>
        </property>
        <property name="staRadioChannel" type="java.lang.String">
            <column name="staRadioChannel" length="30">
                <comment>用户接入信道</comment>
            </column>
        </property>
        <property name="staVlanId" type="java.lang.String">
            <column name="staVlanId" length="30">
                <comment>用户vlan ID</comment>
            </column>
        </property>
        <property name="accessTime" type="java.lang.String">
            <column name="accessTime" length="30">
                <comment>用户接入时间</comment>
            </column>
        </property>
        <property name="onlineTime" type="java.lang.String">
            <column name="onlineTime" length="30">
                <comment>用户在线时长</comment>
            </column>
        </property>
        <property name="staSignalStrengt" type="java.lang.String">
            <column name="StaSignalStrengt" length="30">
                <comment>信号强度</comment>
            </column>
        </property>
        <property name="snr" type="java.lang.String">
            <column name="snr" length="30">
                <comment>信噪比</comment>
            </column>
        </property>
        <property name="staSendByte" type="java.lang.String">
            <column name="staSendByte" length="30">
                <comment>用户发送字节数（上行流量）</comment>
            </column>
        </property>
        <property name="staReceByte" type="java.lang.String">
            <column name="staReceByte" length="30">
                <comment>用户接收字节数（下行流量）</comment>
            </column>
        </property>
        <property name="staSendPack" type="java.lang.String">
            <column name="staSendPack" length="30">
                <comment>用户发送包数</comment>
            </column>
        </property>
        <property name="staRecePack" type="java.lang.String">
            <column name="staRecePack" length="30">
                <comment>用户接收包数</comment>
            </column>
        </property>
        <property name="staRepSendPack" type="java.lang.String">
            <column name="staRepSendPack" length="30">
                <comment>用户重传包数</comment>
            </column>
        </property>
        <property name="staRepSendByte" type="java.lang.String">
            <column name="staRepSendByte" length="30">
                <comment>用户重传字节数</comment>
            </column>
        </property>
        <property name="staSendSpeed" type="java.lang.String">
            <column name="staSendSpeed" length="30">
                <comment>用户发送速率</comment>
            </column>
        </property>
        <property name="staReceSpeed" type="java.lang.String">
            <column name="staReceSpeed" length="30">
                <comment>用户接收速率</comment>
            </column>
        </property>
        <property name="staAllThroughput" type="java.lang.String">
            <column name="staAllThroughput" length="30" />
        </property>
        <property name="staType" type="java.lang.String">
            <column name="staType" length="30">
                <comment>station type: PC/Mobile</comment>
            </column>
        </property>
        <property name="deviceManufacturer" type="java.lang.String">
            <column name="deviceManufacturer" length="30">
                <comment>device manufacturer</comment>
            </column>
        </property>
        <property name="deviceModel" type="java.lang.String">
            <column name="deviceModel" length="30">
                <comment>operating system version</comment>
            </column>
        </property>
        <property name="osVersion" type="java.lang.String">
            <column name="osVersion" length="30">
                <comment>mobile model</comment>
            </column>
        </property>
    </class>
</hibernate-mapping>
